<?xml version="1.0" encoding="utf-8" ?>
<dwsync>
<file name="2e13dae3a6df9604ae4f68b30771dcbc.jpg" server="119.29.114.139//html/" local="131451081507376849" remote="131451160800000000" Dst="0" />
<file name="d650aa5a438961872a2028d813a3b875.jpg" server="119.29.114.139//html/" local="131451081338319763" remote="131451160800000000" Dst="0" />
<file name="download.svg" server="119.29.114.139//html/" local="131451122883737390" remote="131451160800000000" Dst="0" />
<file name="ZtugNa.jpg" server="119.29.114.139//html/" local="131450889988617480" remote="131451160800000000" Dst="0" />
<file name="分享.svg" server="119.29.114.139//html/" local="131451262057714913" remote="131451286800000000" Dst="0" />
<file name="flaged.svg" server="119.29.114.139//html/" local="131451275536472419" remote="131451286800000000" Dst="0" />
<file name="flag.svg" server="119.29.114.139//html/" local="131451120898320090" remote="131451286800000000" Dst="0" />
<file name="212. Flag - 副本.svg" server="119.29.114.139//html/" local="131451120898320090" remote="131451286800000000" Dst="0" />
</dwsync>